{
  "sections": {
    "heading": {
      "type": "heading-template",
      "settings": {
        "use_specify_image": true,
        "parallax": false,
        "color": "#000000",
        "overlay": 54,
        "padding": 50,
        "paddingmb": 50,
        "mg_b": 50,
        "mg_bmb": 50,
        "content_align": "t4s-text-center",
        "bg_pos": "center center",
        "bg_repeat": "no-repeat",
        "bg_size": "cover",
        "use_cus_css": false,
        "code_cus_css": ".SectionID {\nbackground-color:red\n}"
      }
    },
    "main": {
      "type": "main-page",
      "disabled": true,
      "settings": {
        "layout": "t4s-container-fluid",
        "cl_bg": "",
        "cl_bg_gradient": "",
        "mg": "60px,,60px,",
        "pd": "",
        "mg_mb": ",,30px,",
        "pd_mb": ""
      }
    },
    "sidebar-page": {
      "type": "sidebar-page",
      "disabled": true,
      "blocks": {
        "f69681ed-b75e-42de-be58-fdf73b3b7e08": {
          "type": "blog_cate",
          "settings": {
            "title": "Blog categories",
            "cat_link_list": "",
            "count": true
          }
        }
      },
      "block_order": [
        "f69681ed-b75e-42de-be58-fdf73b3b7e08"
      ],
      "settings": {
        "enable_drawer": false,
        "space": 50,
        "size": "medium",
        "br_style": "none",
        "brcolor": "#222222",
        "sidebar_bdr": 5,
        "sidebar_pd": 10
      }
    },
    "68f5f16b-2f3a-43db-8f73-a2ec24cb257e": {
      "type": "hero_image",
      "settings": {
        "se_height": "t4s_ratioadapt",
        "custom_dk": true,
        "height_dk": 600,
        "custom_tb": true,
        "height_tb": 400,
        "custom_mb": true,
        "height_mb": 250,
        "image": "shopify:\/\/shop_images\/Superior_GaN_Tech_Bolder_Faster_Chargers.png",
        "parallax": false,
        "image_position": "0",
        "link_img1": "",
        "open_link": "_blank",
        "text_align": "center",
        "text_align_mb": "center",
        "content_width": "auto",
        "cv_pos": 50,
        "ch_pos": 50,
        "cv_pos_mb": 50,
        "ch_pos_mb": 50,
        "bg_overlay": "#000000",
        "bg_opacity": 0,
        "bg_content_cl": "#ffffff",
        "bg_content_op": 0,
        "content_pd_tb": 15,
        "content_pd_lr": 15,
        "content_pd_tb_mb": 10,
        "content_pd_lr_mb": 10,
        "border_bl": false,
        "br_color": "#222222",
        "br_bg": "#ffffff",
        "br_opacity": 50,
        "br_style": "solid",
        "br_pd": 20,
        "br_pd_mb": 10,
        "time_animation": 1,
        "animation_delay": 40,
        "layout": "t4s-container-fluid",
        "cl_bg": "",
        "cl_bg_gradient": "",
        "mg": "",
        "pd": "",
        "mg_mb": ",,30px,",
        "pd_mb": "",
        "use_cus_css": false,
        "code_cus_css": ""
      }
    },
    "867d840b-8b98-4e54-8f6c-cf49c0ae958b": {
      "type": "slideshow",
      "blocks": {
        "template--14472078393406__867d840b-8b98-4e54-8f6c-cf49c0ae958b-1666662539e143751c-0": {
          "type": "image_parent",
          "settings": {
            "image": "shopify:\/\/shop_images\/Thermal_Guard.png",
            "image_position": "8",
            "cl_img": "",
            "link_img1": "",
            "open_link": "_blank",
            "animate_slide": "none",
            "text_align": "start",
            "text_align_mb": "start",
            "content_width": "container",
            "cv_pos": 50,
            "ch_pos": 25,
            "cv_pos_mb": 50,
            "ch_pos_mb": 54,
            "bg_overlay": "#000000",
            "bg_opacity": 0,
            "bg_content_cl": "#000000",
            "bg_content_op": 0,
            "content_pd_tb": 15,
            "content_pd_lr": 150,
            "content_pd_tb_mb": 10,
            "content_pd_lr_mb": 10,
            "border_bl": false,
            "br_color": "#222222",
            "br_bg": "#ffffff",
            "br_opacity": 50,
            "br_style": "solid",
            "br_pd": 20,
            "br_pd_mb": 10,
            "time_animation": 1,
            "animation_delay": 40
          }
        },
        "657b0022-9cda-44d2-85c4-1399996fec6b": {
          "type": "custom_text",
          "settings": {
            "text": "Thermal Guard™",
            "remove_br_tag": false,
            "fontf": "inherit",
            "text_cl": "#fff",
            "text_fs": 64,
            "text_lh": 75,
            "text_fw": 900,
            "text_ls": 0,
            "text_mgb": 15,
            "font_italic": false,
            "text_shadow": false,
            "hidden_mobile": false,
            "text_fs_mb": 16,
            "text_lh_mb": 0,
            "text_ls_mb": 0,
            "text_mgb_mobile": 10,
            "animation": "none"
          }
        },
        "18e16f69-7c00-42c3-9782-2371fc39e78a": {
          "type": "custom_text",
          "settings": {
            "text": "Protection Technology",
            "remove_br_tag": false,
            "fontf": "inherit",
            "text_cl": "#fff",
            "text_fs": 40,
            "text_lh": 40,
            "text_fw": 600,
            "text_ls": 0,
            "text_mgb": 30,
            "font_italic": false,
            "text_shadow": false,
            "hidden_mobile": false,
            "text_fs_mb": 16,
            "text_lh_mb": 0,
            "text_ls_mb": 0,
            "text_mgb_mobile": 10,
            "animation": "none"
          }
        },
        "47e8b3f2-663a-49a1-996d-b6b0b96e86a2": {
          "type": "custom_text",
          "settings": {
            "text": "Dedicated to increasing safety significantly compared to previous technology, protect you devices with our temperature-monitoring proprietary Thermal GuardTM technology.",
            "remove_br_tag": false,
            "fontf": "inherit",
            "text_cl": "#fff",
            "text_fs": 20,
            "text_lh": 30,
            "text_fw": 400,
            "text_ls": 0,
            "text_mgb": 15,
            "font_italic": false,
            "text_shadow": false,
            "hidden_mobile": false,
            "text_fs_mb": 16,
            "text_lh_mb": 0,
            "text_ls_mb": 0,
            "text_mgb_mobile": 10,
            "animation": "none"
          }
        },
        "template--14472078393406__867d840b-8b98-4e54-8f6c-cf49c0ae958b-1666662539e143751c-4": {
          "type": "image_parent",
          "settings": {
            "image": "shopify:\/\/shop_images\/GaN_Chips.png",
            "image_position": "8",
            "cl_img": "",
            "link_img1": "",
            "open_link": "_blank",
            "animate_slide": "none",
            "text_align": "start",
            "text_align_mb": "center",
            "content_width": "auto",
            "cv_pos": 50,
            "ch_pos": 50,
            "cv_pos_mb": 50,
            "ch_pos_mb": 50,
            "bg_overlay": "#000000",
            "bg_opacity": 0,
            "bg_content_cl": "#ffffff",
            "bg_content_op": 0,
            "content_pd_tb": 15,
            "content_pd_lr": 15,
            "content_pd_tb_mb": 10,
            "content_pd_lr_mb": 10,
            "border_bl": false,
            "br_color": "#222222",
            "br_bg": "#ffffff",
            "br_opacity": 50,
            "br_style": "solid",
            "br_pd": 20,
            "br_pd_mb": 10,
            "time_animation": 1,
            "animation_delay": 40
          }
        }
      },
      "block_order": [
        "template--14472078393406__867d840b-8b98-4e54-8f6c-cf49c0ae958b-1666662539e143751c-0",
        "657b0022-9cda-44d2-85c4-1399996fec6b",
        "18e16f69-7c00-42c3-9782-2371fc39e78a",
        "47e8b3f2-663a-49a1-996d-b6b0b96e86a2",
        "template--14472078393406__867d840b-8b98-4e54-8f6c-cf49c0ae958b-1666662539e143751c-4"
      ],
      "settings": {
        "se_height": "t4s_ratioadapt",
        "custom_dk": true,
        "height_dk": 600,
        "custom_tb": true,
        "height_tb": 400,
        "custom_mb": true,
        "height_mb": 250,
        "eff": "slide",
        "loop": true,
        "au_time": 0,
        "au_hover": true,
        "nav_btn": true,
        "btn_vi": "hover",
        "btn_owl": "simple",
        "btn_shape": "round",
        "btn_cl": "custom2",
        "btn_size": "small",
        "btn_hidden_mobile": false,
        "nav_dot": true,
        "dot_owl": "elessi",
        "dots_cl": "light",
        "dots_round": true,
        "dots_space": 10,
        "dots_hidden_mobile": false,
        "layout": "t4s-container-fluid",
        "cl_bg": "",
        "cl_bg_gradient": "",
        "mg": "",
        "pd": "",
        "mg_mb": ",,30px,",
        "pd_mb": "",
        "use_cus_css": false,
        "code_cus_css": ""
      }
    }
  },
  "order": [
    "heading",
    "main",
    "sidebar-page",
    "68f5f16b-2f3a-43db-8f73-a2ec24cb257e",
    "867d840b-8b98-4e54-8f6c-cf49c0ae958b"
  ]
}
